Metadata-Version: 2.1
Name: diffxpy
Version: 0.7.4
Summary: Fast and scalable differential expression analysis on single-cell RNA-seq data
Home-page: UNKNOWN
Author: David S. Fischer, Florian R. Hölzlwimmer
Author-email: david.fischer@helmholtz-muenchen.de, diffxpy@frhoelzlwimmer.de
License: UNKNOWN
Platform: UNKNOWN
Provides-Extra: docs
Provides-Extra: plotting_deps
Provides-Extra: optional
Requires-Dist: numpy (>=1.16.4)
Requires-Dist: scipy (>=1.2.1)
Requires-Dist: pandas
Requires-Dist: patsy (>=0.5.0)
Requires-Dist: batchglm (>=0.7.4)
Requires-Dist: statsmodels
Provides-Extra: docs
Requires-Dist: sphinx; extra == 'docs'
Requires-Dist: sphinx-autodoc-typehints; extra == 'docs'
Requires-Dist: sphinx-rtd-theme; extra == 'docs'
Requires-Dist: jinja2; extra == 'docs'
Requires-Dist: docutils; extra == 'docs'
Provides-Extra: optional
Requires-Dist: anndata; extra == 'optional'
Provides-Extra: plotting_deps
Requires-Dist: seaborn; extra == 'plotting_deps'
Requires-Dist: matplotlib; extra == 'plotting_deps'
